contextqa/__init__.py
contextqa/alembic.ini
contextqa/cli.py
contextqa/main.py
contextqa/agents/__init__.py
contextqa/agents/tools.py
contextqa/alembic/README
contextqa/alembic/env.py
contextqa/alembic/script.py.mako
contextqa/alembic/versions/0bb7d192c063_initial_migration.py
contextqa/alembic/versions/3058bf204a05_unique_index_name.py
contextqa/alembic/versions/b7d862d599fe_support_for_store_types_and_related_.py
contextqa/models/__init__.py
contextqa/models/orm.py
contextqa/models/schemas.py
contextqa/routes/__init__.py
contextqa/routes/conversational.py
contextqa/routes/dependencies.py
contextqa/routes/qa.py
contextqa/routes/settings.py
contextqa/routes/sources.py
contextqa/routes/status.py
contextqa/services/__init__.py
contextqa/services/chat.py
contextqa/services/context.py
contextqa/services/db.py
contextqa/services/settings.py
contextqa/services/sources.py
contextqa/services/status.py
contextqa/static/notification.mp3
contextqa/ui/contextqa.ico
contextqa/ui/index.html
contextqa/ui/css/175.c46254aa.css
contextqa/ui/css/app.e826dca3.css
contextqa/ui/css/chunk-vendors.9c007bd1.css
contextqa/ui/fonts/primeicons.0112589c.ttf
contextqa/ui/fonts/primeicons.ba3f916d.woff2
contextqa/ui/fonts/primeicons.f8b9e8a4.woff
contextqa/ui/fonts/primeicons.ffecb254.eot
contextqa/ui/images/bug.svg
contextqa/ui/images/chroma.png
contextqa/ui/images/google.png
contextqa/ui/images/logo.png
contextqa/ui/images/mysql.png
contextqa/ui/images/openai.png
contextqa/ui/images/pinecone.png
contextqa/ui/images/redis.svg
contextqa/ui/images/sqlite.png
contextqa/ui/images/title.png
contextqa/ui/images/user.png
contextqa/ui/img/primeicons.943ab24c.svg
contextqa/ui/js/175.2f41546f.js
contextqa/ui/js/175.2f41546f.js.map
contextqa/ui/js/app.14ea058b.js
contextqa/ui/js/app.14ea058b.js.map
contextqa/ui/js/chunk-vendors.b181949f.js
contextqa/ui/js/chunk-vendors.b181949f.js.map
contextqa/utils/__init__.py
contextqa/utils/clients.py
contextqa/utils/exceptions.py
contextqa/utils/memory.py
contextqa-2.0.5.dist-info/METADATA
contextqa-2.0.5.dist-info/WHEEL
contextqa-2.0.5.dist-info/entry_points.txt
contextqa-2.0.5.dist-info/top_level.txt
contextqa-2.0.5.dist-info/RECORD
